numfun/__init__.py
numfun/barycentric.py
numfun/chebyshev.py
numfun/function.py
numfun/funutils.py
numfun/polyfit.py
numfun-0.0.1.dist-info/LICENSE
numfun-0.0.1.dist-info/METADATA
numfun-0.0.1.dist-info/WHEEL
numfun-0.0.1.dist-info/top_level.txt
numfun-0.0.1.dist-info/RECORD
