Metadata-Version: 2.1
Name: numfun
Version: 0.0.1
Summary: Numerical computing with functions
Home-page: https://github.com/mhsnjvd/funpy
Author: Mohsin Javed
Author-email: mhsnjvd@gmail.com
License: UNKNOWN
Platform: UNKNOWN
Classifier: Programming Language :: Python :: 3
Classifier: License :: OSI Approved :: MIT License
Classifier: Operating System :: OS Independent
Requires-Python: >=3.6
